<annotation>
	<folder></folder>
	<filename>bengal-829-_jpg.rf.86568313f0be8d43c9b239f56abb8ca8.jpg</filename>
	<path>bengal-829-_jpg.rf.86568313f0be8d43c9b239f56abb8ca8.jpg</path>
	<source>
		<database>roboflow.ai</database>
	</source>
	<size>
		<width>300</width>
		<height>353</height>
		<depth>3</depth>
	</size>
	<segmented>0</segmented>
	<object>
		<name>bengal</name>
		<pose>Unspecified</pose>
		<truncated>0</truncated>
		<difficult>0</difficult>
		<occluded>0</occluded>
		<bndbox>
			<xmin>90</xmin>
			<xmax>251</xmax>
			<ymin>30</ymin>
			<ymax>197</ymax>
		</bndbox>
	</object>
</annotation>
