<annotation>
	<folder></folder>
	<filename>ragdoll-583-_jpg.rf.0807790be4cccbc5681409e8911e16a8.jpg</filename>
	<path>ragdoll-583-_jpg.rf.0807790be4cccbc5681409e8911e16a8.jpg</path>
	<source>
		<database>roboflow.ai</database>
	</source>
	<size>
		<width>300</width>
		<height>400</height>
		<depth>3</depth>
	</size>
	<segmented>0</segmented>
	<object>
		<name>ragdoll</name>
		<pose>Unspecified</pose>
		<truncated>0</truncated>
		<difficult>0</difficult>
		<occluded>0</occluded>
		<bndbox>
			<xmin>1</xmin>
			<xmax>233</xmax>
			<ymin>1</ymin>
			<ymax>259</ymax>
		</bndbox>
	</object>
</annotation>
