<annotation>
	<folder></folder>
	<filename>persian-38-_jpg.rf.312f2d64b877b0658475699ea4b99ae3.jpg</filename>
	<path>persian-38-_jpg.rf.312f2d64b877b0658475699ea4b99ae3.jpg</path>
	<source>
		<database>roboflow.ai</database>
	</source>
	<size>
		<width>375</width>
		<height>500</height>
		<depth>3</depth>
	</size>
	<segmented>0</segmented>
	<object>
		<name>persian</name>
		<pose>Unspecified</pose>
		<truncated>0</truncated>
		<difficult>0</difficult>
		<occluded>0</occluded>
		<bndbox>
			<xmin>1</xmin>
			<xmax>369</xmax>
			<ymin>1</ymin>
			<ymax>314</ymax>
		</bndbox>
	</object>
</annotation>
