<annotation>
	<folder></folder>
	<filename>persian-455-_jpg.rf.adc02ca49589504deb00097e3ea9ff26.jpg</filename>
	<path>persian-455-_jpg.rf.adc02ca49589504deb00097e3ea9ff26.jpg</path>
	<source>
		<database>roboflow.ai</database>
	</source>
	<size>
		<width>300</width>
		<height>300</height>
		<depth>3</depth>
	</size>
	<segmented>0</segmented>
	<object>
		<name>persian</name>
		<pose>Unspecified</pose>
		<truncated>0</truncated>
		<difficult>0</difficult>
		<occluded>0</occluded>
		<bndbox>
			<xmin>8</xmin>
			<xmax>86</xmax>
			<ymin>5</ymin>
			<ymax>85</ymax>
		</bndbox>
	</object>
</annotation>
