<annotation>
	<folder></folder>
	<filename>rblue-644-_jpg.rf.ca7c36845678071ea48cba36a7156f7d.jpg</filename>
	<path>rblue-644-_jpg.rf.ca7c36845678071ea48cba36a7156f7d.jpg</path>
	<source>
		<database>roboflow.ai</database>
	</source>
	<size>
		<width>300</width>
		<height>400</height>
		<depth>3</depth>
	</size>
	<segmented>0</segmented>
	<object>
		<name>rblue</name>
		<pose>Unspecified</pose>
		<truncated>0</truncated>
		<difficult>0</difficult>
		<occluded>0</occluded>
		<bndbox>
			<xmin>55</xmin>
			<xmax>196</xmax>
			<ymin>89</ymin>
			<ymax>237</ymax>
		</bndbox>
	</object>
</annotation>
