<annotation>
	<folder></folder>
	<filename>ragdoll-96-_jpg.rf.d9704ef902cf1b83263231316f38db84.jpg</filename>
	<path>ragdoll-96-_jpg.rf.d9704ef902cf1b83263231316f38db84.jpg</path>
	<source>
		<database>roboflow.ai</database>
	</source>
	<size>
		<width>500</width>
		<height>500</height>
		<depth>3</depth>
	</size>
	<segmented>0</segmented>
	<object>
		<name>ragdoll</name>
		<pose>Unspecified</pose>
		<truncated>0</truncated>
		<difficult>0</difficult>
		<occluded>0</occluded>
		<bndbox>
			<xmin>164</xmin>
			<xmax>436</xmax>
			<ymin>34</ymin>
			<ymax>239</ymax>
		</bndbox>
	</object>
</annotation>
