<annotation>
	<folder></folder>
	<filename>rblue-100-_jpg.rf.15b91810008cdbd9be8e57ea251b6624.jpg</filename>
	<path>rblue-100-_jpg.rf.15b91810008cdbd9be8e57ea251b6624.jpg</path>
	<source>
		<database>roboflow.ai</database>
	</source>
	<size>
		<width>500</width>
		<height>500</height>
		<depth>3</depth>
	</size>
	<segmented>0</segmented>
	<object>
		<name>rblue</name>
		<pose>Unspecified</pose>
		<truncated>0</truncated>
		<difficult>0</difficult>
		<occluded>0</occluded>
		<bndbox>
			<xmin>293</xmin>
			<xmax>501</xmax>
			<ymin>40</ymin>
			<ymax>254</ymax>
		</bndbox>
	</object>
</annotation>
