<annotation>
	<folder></folder>
	<filename>persian-371-_jpg.rf.6216daf286701b99cb089a920e81664a.jpg</filename>
	<path>persian-371-_jpg.rf.6216daf286701b99cb089a920e81664a.jpg</path>
	<source>
		<database>roboflow.ai</database>
	</source>
	<size>
		<width>300</width>
		<height>420</height>
		<depth>3</depth>
	</size>
	<segmented>0</segmented>
	<object>
		<name>persian</name>
		<pose>Unspecified</pose>
		<truncated>0</truncated>
		<difficult>0</difficult>
		<occluded>0</occluded>
		<bndbox>
			<xmin>69</xmin>
			<xmax>268</xmax>
			<ymin>1</ymin>
			<ymax>173</ymax>
		</bndbox>
	</object>
</annotation>
