<annotation>
	<folder></folder>
	<filename>persian-181-_jpg.rf.a5bbd8b1287a0e875a9d9ff7b46c6378.jpg</filename>
	<path>persian-181-_jpg.rf.a5bbd8b1287a0e875a9d9ff7b46c6378.jpg</path>
	<source>
		<database>roboflow.ai</database>
	</source>
	<size>
		<width>300</width>
		<height>400</height>
		<depth>3</depth>
	</size>
	<segmented>0</segmented>
	<object>
		<name>persian</name>
		<pose>Unspecified</pose>
		<truncated>0</truncated>
		<difficult>0</difficult>
		<occluded>0</occluded>
		<bndbox>
			<xmin>136</xmin>
			<xmax>234</xmax>
			<ymin>165</ymin>
			<ymax>247</ymax>
		</bndbox>
	</object>
</annotation>
