<annotation>
	<folder></folder>
	<filename>maxresdefault_jpg.rf.0c165a846ec6d1fefb9269ccc03f7424.jpg</filename>
	<path>maxresdefault_jpg.rf.0c165a846ec6d1fefb9269ccc03f7424.jpg</path>
	<source>
		<database>roboflow.ai</database>
	</source>
	<size>
		<width>1280</width>
		<height>720</height>
		<depth>3</depth>
	</size>
	<segmented>0</segmented>
	<object>
		<name>ragdoll</name>
		<pose>Unspecified</pose>
		<truncated>0</truncated>
		<difficult>0</difficult>
		<occluded>0</occluded>
		<bndbox>
			<xmin>27</xmin>
			<xmax>357</xmax>
			<ymin>107</ymin>
			<ymax>422</ymax>
		</bndbox>
	</object>
</annotation>
