<annotation>
	<folder></folder>
	<filename>persian-176-_jpg.rf.931de085e8ec1b5bcef5484b962c32dc.jpg</filename>
	<path>persian-176-_jpg.rf.931de085e8ec1b5bcef5484b962c32dc.jpg</path>
	<source>
		<database>roboflow.ai</database>
	</source>
	<size>
		<width>320</width>
		<height>480</height>
		<depth>3</depth>
	</size>
	<segmented>0</segmented>
	<object>
		<name>persian</name>
		<pose>Unspecified</pose>
		<truncated>0</truncated>
		<difficult>0</difficult>
		<occluded>0</occluded>
		<bndbox>
			<xmin>32</xmin>
			<xmax>321</xmax>
			<ymin>11</ymin>
			<ymax>261</ymax>
		</bndbox>
	</object>
</annotation>
